flutil/__init__.py
flutil/annotation/__init__.py
flutil/annotation/parser.py
flutil/annotation/folder/__init__.py
flutil/annotation/maika_ref/__init__.py
flutil/annotation/no_annot/__init__.py
flutil/annotation/open_reid/__init__.py
flutil/annotation/pascal/__init__.py
flutil/annotation/underscore_x2/__init__.py
flutil/classifier/__init__.py
flutil/classifier/evaluator.py
flutil/classifier/cos/__init__.py
flutil/classifier/decision_tree/__init__.py
flutil/classifier/euclid/__init__.py
flutil/classifier/knn/__init__.py
flutil/classifier/svm/__init__.py
flutil/color/__init__.py
flutil/color/colortest.py
flutil/color/xkcd.py
flutil/demo/__init__.py
flutil/demo/inputter.py
flutil/demo/outputter.py
flutil/demo/processor.py
flutil/detect/__init__.py
flutil/detect/_detection.py
flutil/detect/_detector.py
flutil/detect/detection_test.py
flutil/detect/face/__init__.py
flutil/detect/face/ageit.py
flutil/detect/face/dlib.py
flutil/detect/face/mtcnn.py
flutil/detect/face/etc/__init__.py
flutil/detect/face/etc/align/__init__.py
flutil/detect/face/etc/align/detect_face.py
flutil/detect/object/__init__.py
flutil/detect/object/lightnet.py
flutil/experiment/__init__.py
flutil/extract/__init__.py
flutil/extract/_extractor.py
flutil/extract/face/__init__.py
flutil/extract/face/ageit.py
flutil/extract/face/dlib.py
flutil/extract/face/facenet.py
flutil/extract/face/inface.py
flutil/extract/face/etc/__init__.py
flutil/extract/face/etc/facenet/__init__.py
flutil/extract/face/etc/facenet/contributed/__init__.py
flutil/extract/face/etc/facenet/contributed/batch_represent.py
flutil/extract/face/etc/facenet/contributed/cluster.py
flutil/extract/face/etc/facenet/contributed/clustering.py
flutil/extract/face/etc/facenet/contributed/export_embeddings.py
flutil/extract/face/etc/facenet/contributed/face.py
flutil/extract/face/etc/facenet/contributed/predict.py
flutil/extract/face/etc/facenet/contributed/real_time_face_recognition.py
flutil/extract/face/etc/facenet/src/__init__.py
flutil-0.0.4.dist-info/LICENSE
flutil-0.0.4.dist-info/METADATA
flutil-0.0.4.dist-info/WHEEL
flutil-0.0.4.dist-info/top_level.txt
flutil-0.0.4.dist-info/RECORD
