Metadata-Version: 2.1
Name: flutil
Version: 0.0.4
Summary: Package with computer vision utilities
Home-page: https://gitlab.com/EAVISE/flutil
Author: Floris De Feyter
Author-email: floris.defeyter@kuleuven.be
License: UNKNOWN
Platform: UNKNOWN
Classifier: Programming Language :: Python :: 3
Classifier: License :: OSI Approved :: MIT License
Classifier: Operating System :: OS Independent
Requires-Python: >=3.6
